README.md
pyproject.toml
setup.py
docker_ops/__init__.py
docker_ops/constants.py
docker_ops/factory.py
docker_ops/scan.py
docker_ops/utils.py
docker_ops.egg-info/PKG-INFO
docker_ops.egg-info/SOURCES.txt
docker_ops.egg-info/dependency_links.txt
docker_ops.egg-info/entry_points.txt
docker_ops.egg-info/not-zip-safe
docker_ops.egg-info/requires.txt
docker_ops.egg-info/top_level.txt