Metadata-Version: 1.2
Name: docker-ops
Version: 0.0.6
Summary: Docker Operations
Home-page: https://github.com/jbcurtin/docker-ops
Author: Joseph Curtin <42@jbcurtin.io
Author-email: docker-ops@jbcurtin.io
License: MIT
Platform: UNKNOWN
Classifier: Operating System :: OS Independent
Classifier: Programming Language :: Python
Classifier: Programming Language :: Python :: 3
Classifier: Programming Language :: Python :: 3.6
Classifier: Programming Language :: Python :: 3.7
Classifier: Programming Language :: Python :: 3 :: Only
Requires-Python: >=3.7
